evalplus/__init__.py
evalplus/_version.py
evalplus/codegen.py
evalplus/config.py
evalplus/evalperf.py
evalplus/evaluate.py
evalplus/inputgen.py
evalplus/lecacy_sanitize.py
evalplus/sanitize.py
evalplus/syncheck.py
evalplus/utils.py
evalplus/data/__init__.py
evalplus/data/humaneval.py
evalplus/data/mbpp.py
evalplus/data/utils.py
evalplus/eval/__init__.py
evalplus/eval/_special_oracle.py
evalplus/eval/utils.py
evalplus/gen/__init__.py
evalplus/gen/chatgpt_gen.py
evalplus/gen/mut_gen.py
evalplus/gen/type_mut.py
evalplus/gen/util/__init__.py
evalplus/gen/util/anthropic_request.py
evalplus/gen/util/openai_request.py
evalplus/perf/__init__.py
evalplus/perf/profile.py
evalplus/perf/sampling.py
evalplus/perf/sas.py
evalplus/perf/select_pe_inputs.py
evalplus/perf/select_pe_tasks.py
evalplus/provider/__init__.py
evalplus/provider/anthropic.py
evalplus/provider/base.py
evalplus/provider/google.py
evalplus/provider/hf.py
evalplus/provider/openai.py
evalplus/provider/utility.py
evalplus/provider/vllm.py
evalplus-0.3.1.dist-info/LICENSE
evalplus-0.3.1.dist-info/METADATA
evalplus-0.3.1.dist-info/WHEEL
evalplus-0.3.1.dist-info/entry_points.txt
evalplus-0.3.1.dist-info/top_level.txt
evalplus-0.3.1.dist-info/RECORD
