Metadata-Version: 2.1
Name: evalplus
Version: 0.3.1
Summary: "EvalPlus for rigourous evaluation of LLM-synthesized code"
Home-page: https://github.com/evalplus/evalplus
License: Apache-2.0
Platform: any
Classifier: Operating System :: OS Independent
Classifier: Programming Language :: Python :: 3
Classifier: License :: OSI Approved :: Apache Software License
Requires-Python: >=3.9
License-File: LICENSE
Requires-Dist: wget>=3.2
Requires-Dist: tempdir>=0.7.1
Requires-Dist: multipledispatch>=0.6.0
Requires-Dist: appdirs>=1.4.4
Requires-Dist: numpy>=1.19.5
Requires-Dist: tqdm>=4.56.0
Requires-Dist: termcolor>=2.0.0
Requires-Dist: fire>=0.6.0
Requires-Dist: openai>=1.11.1
Requires-Dist: tree_sitter>=0.22.0
Requires-Dist: tree-sitter-python>=0.21.0
Requires-Dist: rich>=12.3.0
Requires-Dist: transformers>=4.43.0
Requires-Dist: stop-sequencer>=1.2.3
Requires-Dist: anthropic>=0.34.1
Requires-Dist: google-generativeai>=0.7.2
Requires-Dist: datasets>=2.21.0
Requires-Dist: psutil>=5.9.0
Provides-Extra: perf
Requires-Dist: Pympler>=1.0.1; extra == "perf"
Requires-Dist: cirron>=0.4; extra == "perf"
Provides-Extra: vllm
Requires-Dist: vllm>=0.5.1; extra == "vllm"
